{"skeleton":{"hash":"d7V50ucGzAc","spine":"4.1.09","x":-1024,"y":-58.15,"width":2048,"height":2048,"images":"","audio":""},"bones":[{"name":"root"},{"name":"bone","parent":"root","x":-103.23,"y":144.73},{"name":"bone2","parent":"bone","x":103.7},{"name":"bone3","parent":"bone2","x":125,"y":5.56},{"name":"bone4","parent":"bone3","x":-225,"y":119.45},{"name":"bone5","parent":"bone4","x":101.85,"y":-11.11},{"name":"bone6","parent":"bone5","x":115.74,"y":3.7},{"name":"bone7","parent":"bone6","x":-206.48,"y":119.45},{"name":"bone8","parent":"bone7","x":94.45,"y":-6.48},{"name":"bone9","parent":"bone8","x":119.45,"y":-1.85},{"name":"bone10","parent":"bone9","x":-214.61,"y":123.45},{"name":"bone11","parent":"bone10","x":103.64,"y":-1.47}],"slots":[{"name":"lightning_0001","bone":"bone","attachment":"lightning_0001"},{"name":"lightning_0002","bone":"bone2","attachment":"lightning_0002"},{"name":"lightning_0003","bone":"bone3","attachment":"lightning_0003"},{"name":"lightning_0004","bone":"bone4","attachment":"lightning_0004"},{"name":"lightning_0005","bone":"bone5","attachment":"lightning_0005"},{"name":"lightning_0006","bone":"bone6","attachment":"lightning_0006"},{"name":"lightning_0007","bone":"bone7","attachment":"lightning_0007"},{"name":"lightning_0008","bone":"bone8","attachment":"lightning_0008"},{"name":"lightning_0009","bone":"bone9","attachment":"lightning_0009"},{"name":"lightning_0010","bone":"bone10","attachment":"lightning_0010"},{"name":"lightning_0011","bone":"bone11","attachment":"lightning_0011"}],"skins":[{"name":"default","attachments":{"lightning_0001":{"lightning_0001":{"x":103.23,"y":821.12,"width":2048,"height":2048}},"lightning_0002":{"lightning_0002":{"x":-0.47,"y":821.12,"width":2048,"height":2048}},"lightning_0003":{"lightning_0003":{"x":-125.48,"y":815.56,"width":2048,"height":2048}},"lightning_0004":{"lightning_0004":{"x":99.53,"y":696.12,"width":2048,"height":2048}},"lightning_0005":{"lightning_0005":{"x":-2.33,"y":707.23,"width":2048,"height":2048}},"lightning_0006":{"lightning_0006":{"x":-118.07,"y":703.52,"width":2048,"height":2048}},"lightning_0007":{"lightning_0007":{"x":88.42,"y":584.08,"width":2048,"height":2048}},"lightning_0008":{"lightning_0008":{"x":-6.03,"y":590.56,"width":2048,"height":2048}},"lightning_0009":{"lightning_0009":{"x":-125.48,"y":592.41,"width":2048,"height":2048}},"lightning_0010":{"lightning_0010":{"x":89.13,"y":468.96,"width":2048,"height":2048}},"lightning_0011":{"lightning_0011":{"x":-14.51,"y":470.43,"width":2048,"height":2048}}}}],"animations":{"bolt":{"slots":{"lightning_0001":{"alpha":[{"value":1,"curve":"stepped"},{"time":0.0333,"value":0}]},"lightning_0002":{"alpha":[{"value":0,"curve":"stepped"},{"time":0.0333,"value":1,"curve":"stepped"},{"time":0.0667,"value":0}]},"lightning_0003":{"alpha":[{"value":0,"curve":"stepped"},{"time":0.0667,"value":1,"curve":"stepped"},{"time":0.1,"value":0}]},"lightning_0004":{"alpha":[{"value":0,"curve":"stepped"},{"time":0.1,"value":1,"curve":"stepped"},{"time":0.1333,"value":0}]},"lightning_0005":{"alpha":[{"value":0,"curve":"stepped"},{"time":0.1333,"value":1,"curve":"stepped"},{"time":0.1667,"value":0}]},"lightning_0006":{"alpha":[{"value":0,"curve":"stepped"},{"time":0.1667,"value":1,"curve":"stepped"},{"time":0.2,"value":0}]},"lightning_0007":{"alpha":[{"value":0,"curve":"stepped"},{"time":0.2,"value":1,"curve":"stepped"},{"time":0.2333,"value":0}]},"lightning_0008":{"alpha":[{"value":0,"curve":"stepped"},{"time":0.2333,"value":1,"curve":"stepped"},{"time":0.2667,"value":0}]},"lightning_0009":{"alpha":[{"value":0,"curve":"stepped"},{"time":0.2667,"value":1,"curve":"stepped"},{"time":0.3,"value":0}]},"lightning_0010":{"alpha":[{"value":0,"curve":"stepped"},{"time":0.3,"value":1,"curve":"stepped"},{"time":0.3333,"value":0}]},"lightning_0011":{"alpha":[{"value":0,"curve":"stepped"},{"time":0.3333,"value":1,"curve":"stepped"},{"time":0.3667,"value":0}]}}}}}